README
helpers.py
setup.cfg
setup.py
trapcamera.py
pybossa_raspberry_trapcamera.egg-info/PKG-INFO
pybossa_raspberry_trapcamera.egg-info/SOURCES.txt
pybossa_raspberry_trapcamera.egg-info/dependency_links.txt
pybossa_raspberry_trapcamera.egg-info/entry_points.txt
pybossa_raspberry_trapcamera.egg-info/requires.txt
pybossa_raspberry_trapcamera.egg-info/top_level.txt
test/test_helpers.py