Metadata-Version: 1.1
Name: pybossa-raspberry-trapcamera
Version: 0.0.5
Summary: PyBossa Raspberry Pi trap camera tool
Home-page: https://github.com/PyBossa/raspberry-trapcamera
Author: SciFabric LTD
Author-email: info@scifabric.com
License: AGPLv3
Platform: UNKNOWN
Classifier: Development Status :: 4 - Beta
Classifier: Environment :: Console
Classifier: Intended Audience :: Developers
Classifier: License :: OSI Approved :: GNU Affero General Public License v3 or later (AGPLv3+)
Classifier: Operating System :: OS Independent
Classifier: Programming Language :: Python
